config/keyvault/__init__.py
config/keyvault/py.typed
essentials_configuration_keyvault-1.0.1.dist-info/METADATA
essentials_configuration_keyvault-1.0.1.dist-info/WHEEL
essentials_configuration_keyvault-1.0.1.dist-info/licenses/LICENSE
essentials_configuration_keyvault-1.0.1.dist-info/RECORD
