Metadata-Version: 2.1
Name: essentials-configuration-keyvault
Version: 1.0.1
Summary: Azure Key Vault source for essentials-configuration.
Project-URL: Homepage, https://github.com/Neoteroi/essentials-configuration-keyvault
Project-URL: Bug Tracker, https://github.com/Neoteroi/essentials-configuration-keyvault/issues
Author-email: Roberto Prevato <roberto.prevato@gmail.com>
License-File: LICENSE
Keywords: Azure Key Vault,configuration,environment,secrets
Classifier: Development Status :: 5 - Production/Stable
Classifier: License :: OSI Approved :: MIT License
Classifier: Operating System :: OS Independent
Classifier: Programming Language :: Python :: 3
Classifier: Programming Language :: Python :: 3.8
Classifier: Programming Language :: Python :: 3.9
Classifier: Programming Language :: Python :: 3.10
Classifier: Programming Language :: Python :: 3.11
Requires-Python: >=3.7
Requires-Dist: azure-identity~=1.12.0
Requires-Dist: azure-keyvault-secrets~=4.7.0
Requires-Dist: essentials-configuration~=2.0.0
